lvsfunc/__init__.py
lvsfunc/_metadata.py
lvsfunc/color.py
lvsfunc/comparison.py
lvsfunc/deblock.py
lvsfunc/debug.py
lvsfunc/exceptions.py
lvsfunc/export.py
lvsfunc/grain.py
lvsfunc/misc.py
lvsfunc/py.typed
lvsfunc/random.py
lvsfunc/scaler.py
lvsfunc/util.py
lvsfunc/dependency/__init__.py
lvsfunc/dependency/exceptions.py
lvsfunc/dependency/function.py
lvsfunc/dependency/packages.py
lvsfunc/dependency/plugin.py
lvsfunc/dependency/types.py
lvsfunc/diff/__init__.py
lvsfunc/diff/enum.py
lvsfunc/diff/func.py
lvsfunc/diff/strategies.py
lvsfunc/diff/types.py
lvsfunc/models/__init__.py
lvsfunc/models/base.py
lvsfunc/models/delowpass.py
lvsfunc/models/dempeg2.py
lvsfunc/models/np.py
lvsfunc/models/shaders/ldempeg2/1x_dempeg2_fp32.onnx
lvsfunc/models/shaders/lhzdelowpass/1x_lanczos_hz_delowpass_4_4_125_1375_mpeg2_fp32.onnx
lvsfunc/models/shaders/lhzdelowpass/1x_lanczos_hz_delowpass_4_4_15_15_fp32.onnx
lvsfunc/models/shaders/lhzdelowpass/1x_lanczos_hz_delowpass_4_4_15_15_mpeg2_fp32.onnx
lvsfunc/nn/__init__.py
lvsfunc/nn/func.py
lvsfunc/nn/util.py
lvsfunc-0.8.6.dist-info/licenses/LICENSE
lvsfunc-0.8.6.dist-info/METADATA
lvsfunc-0.8.6.dist-info/WHEEL
lvsfunc-0.8.6.dist-info/top_level.txt
lvsfunc-0.8.6.dist-info/RECORD
