Metadata-Version: 2.4
Name: lvsfunc
Version: 0.8.6
Summary: Light's Vapoursynth Functions.
Author: LightArrowsEXE
Author-email: LightArrowsReboot@gmail.com
Maintainer: LightArrowsEXE
Maintainer-email: LightArrowsReboot@gmail.com
Project-URL: Source Code, https://github.com/Jaded-Encoding-Thaumaturgy/lvsfunc
Project-URL: Contact, https://discord.gg/XTpc6Fa9eB
Classifier: Natural Language :: English
Classifier: Intended Audience :: Developers
Classifier: Intended Audience :: Other Audience
Classifier: Programming Language :: Python :: 3.10
Classifier: License :: OSI Approved :: MIT License
Classifier: Operating System :: OS Independent
Classifier: Typing :: Typed
Classifier: Topic :: Multimedia :: Video
Classifier: Topic :: Multimedia :: Video :: Display
Requires-Python: >=3.12
License-File: LICENSE
Requires-Dist: VapourSynth>=68
Requires-Dist: vsjetpack>=0.3.4
Requires-Dist: numpy>=2.1.1
Dynamic: author
Dynamic: author-email
Dynamic: classifier
Dynamic: description
Dynamic: description-content-type
Dynamic: license-file
Dynamic: maintainer
Dynamic: maintainer-email
Dynamic: project-url
Dynamic: requires-dist
Dynamic: requires-python
Dynamic: summary
